arrand-0.2.0.dist-info/licenses/AUTHORS.md
arrand-0.2.0.dist-info/licenses/LICENSE
data/__init__.py
data/ayas.txt
data/hadiths.txt
data/phrases.txt
data/poems.txt
data/proverbs.txt
data/texts.txt
data/words.txt
data/vocalized/__init__.py
data/vocalized/ayas.txt
data/vocalized/hadiths.txt
data/vocalized/phrases.txt
data/vocalized/poems.txt
data/vocalized/proverbs.txt
data/vocalized/texts.txt
data/vocalized/words.txt
arrand-0.2.0.dist-info/METADATA
arrand-0.2.0.dist-info/WHEEL
arrand-0.2.0.dist-info/entry_points.txt
arrand-0.2.0.dist-info/top_level.txt
arrand-0.2.0.dist-info/RECORD
