Metadata-Version: 2.4
Name: arrand
Version: 0.2.0
Summary: Arrand: random Arabic text generator
Author-email: Taha Zerrouki <taha.zerrouki@gmail.com>
License: GPL
Project-URL: Homepage, http://arrand.sourceforge.net/
Classifier: Development Status :: 5 - Production/Stable
Classifier: Intended Audience :: End Users/Desktop
Classifier: Operating System :: OS Independent
Classifier: Programming Language :: Python
Requires-Python: >=3.6
License-File: LICENSE
License-File: AUTHORS.md
Requires-Dist: pyarabic>=0.6.8
Requires-Dist: importlib_resources; python_version < "3.7"
Dynamic: license-file
